COPYING
CREDITS.rst
ChangeLog
MANIFEST.in
README.rst
TODO.rst
gsl_packages.py
pyproject.toml
setup.cfg
setup.py
Include/pygsl/block_helpers.h
Include/pygsl/block_helpers_numpy.h
Include/pygsl/capsuletrunk.h
Include/pygsl/compilers.h
Include/pygsl/complex_helpers.h
Include/pygsl/error_helpers.h
Include/pygsl/errorno.h
Include/pygsl/function_helpers.h
Include/pygsl/general_helpers.h
Include/pygsl/intern.h
Include/pygsl/numpy_api_version.h
Include/pygsl/old_numpy_compat.h
Include/pygsl/profile.h
Include/pygsl/pygsl.h
Include/pygsl/pygsl_features.h
Include/pygsl/rng.h
Include/pygsl/rng_helpers.h
Include/pygsl/solver.h
Include/pygsl/string_helpers.h
Include/pygsl/transition.h
Include/pygsl/utils.h
doc/Makefile
doc/README
doc/README-Distributors.html
doc/README-RPM
doc/conf.py
doc/index.rst
doc/release_checklist.rst
doc/api/pygsl.rst
doc/api/pygsl.statistics.rst
doc/api/pygsl.testing.rst
doc/api/sf_func.rst
doc/api/sf/sf__airy_doc.rst
doc/api/sf/sf__bessel_doc.rst
doc/api/sf/sf__clausen_doc.rst
doc/api/sf/sf__coulomb_doc.rst
doc/api/sf/sf__coupling_doc.rst
doc/api/sf/sf__dawson_doc.rst
doc/api/sf/sf__debye_doc.rst
doc/api/sf/sf__dilog_doc.rst
doc/api/sf/sf__elementary_doc.rst
doc/api/sf/sf__ellint_doc.rst
doc/api/sf/sf__elljac_doc.rst
doc/api/sf/sf__erf_doc.rst
doc/api/sf/sf__exp_doc.rst
doc/api/sf/sf__fermi_dirac_doc.rst
doc/api/sf/sf__gamma_doc.rst
doc/api/sf/sf__gegenpoly_doc.rst
doc/api/sf/sf__gsl_complex_doc.rst
doc/api/sf/sf__hermite_doc.rst
doc/api/sf/sf__hydrogenic_doc.rst
doc/api/sf/sf__hyperg_doc.rst
doc/api/sf/sf__laguerre_doc.rst
doc/api/sf/sf__lambert_doc.rst
doc/api/sf/sf__legendre_doc.rst
doc/api/sf/sf__log_doc.rst
doc/api/sf/sf__math_doc.rst
doc/api/sf/sf__mathieu_doc.rst
doc/api/sf/sf__misc_doc.rst
doc/api/sf/sf__poch_doc.rst
doc/api/sf/sf__pow_doc.rst
doc/api/sf/sf__psi_doc.rst
doc/api/sf/sf__synchrotron_doc.rst
doc/api/sf/sf__transport_doc.rst
doc/api/sf/sf__trig_doc.rst
doc/api/sf/sf__zeta_doc.rst
doc/ref/chebyshev.rst
doc/ref/const.rst
pygsl.egg-info/PKG-INFO
pygsl.egg-info/SOURCES.txt
pygsl.egg-info/dependency_links.txt
pygsl.egg-info/requires.txt
pygsl.egg-info/top_level.txt
